topsis/__init__.py
topsis/topsis.py
Topsis_Nikunj_102003362-1.0.8.dist-info/License.txt
Topsis_Nikunj_102003362-1.0.8.dist-info/METADATA
Topsis_Nikunj_102003362-1.0.8.dist-info/WHEEL
Topsis_Nikunj_102003362-1.0.8.dist-info/entry_points.txt
Topsis_Nikunj_102003362-1.0.8.dist-info/top_level.txt
Topsis_Nikunj_102003362-1.0.8.dist-info/RECORD
